weni/__init__.py
weni/profilers/__init__.py
weni/profilers/cprofiler_middleware.py
weni_profilers-0.0.2.dist-info/LICENSE.txt
weni_profilers-0.0.2.dist-info/METADATA
weni_profilers-0.0.2.dist-info/WHEEL
weni_profilers-0.0.2.dist-info/RECORD
